python_distributed/__init__.py
python_distributed/hello.py
test_publish_hello_world-0.0.1.dist-info/METADATA
test_publish_hello_world-0.0.1.dist-info/WHEEL
test_publish_hello_world-0.0.1.dist-info/RECORD
